persian_admin/__init__.py
persian_admin/admin.py
persian_admin/apps.py
persian_admin/cache.py
persian_admin/compat.py
persian_admin/models.py
persian_admin/tests.py
persian_admin/version.py
persian_admin/migrations/0001_initial.py
persian_admin/migrations/0002_alter_font_font.py
persian_admin/migrations/0003_rename_font_font_name.py
persian_admin/migrations/0004_alter_font_name.py
persian_admin/migrations/0005_alter_font_name.py
persian_admin/migrations/__init__.py
persian_admin/templatetags/__init__.py
persian_admin/templatetags/persian_admin_tags.py
django_persian_admin_panel-1.0.dist-info/LICENSE
django_persian_admin_panel-1.0.dist-info/METADATA
django_persian_admin_panel-1.0.dist-info/WHEEL
django_persian_admin_panel-1.0.dist-info/top_level.txt
django_persian_admin_panel-1.0.dist-info/RECORD
